timer_cli/__init__.py
timer_cli/auth.py
timer_cli/job.py
timer_cli/main.py
timer_cli/output.py
timer_cli/transfer.py
globus_timer_cli-0.2.9.post0.dist-info/LICENSE
globus_timer_cli-0.2.9.post0.dist-info/METADATA
globus_timer_cli-0.2.9.post0.dist-info/WHEEL
globus_timer_cli-0.2.9.post0.dist-info/entry_points.txt
globus_timer_cli-0.2.9.post0.dist-info/RECORD
